docs/source/conf.py
ms_entropy/__init__.py
ms_entropy/version.py
ms_entropy/entropy_search/__init__.py
ms_entropy/entropy_search/fast_flash_entropy_search.py
ms_entropy/entropy_search/fast_flash_entropy_search_cpython.cp38-win_amd64.pyd
ms_entropy/entropy_search/flash_entropy_search.py
ms_entropy/entropy_search/flash_entropy_search_core.py
ms_entropy/entropy_search/flash_entropy_search_core_for_dynamic_indexing.py
ms_entropy/entropy_search/flash_entropy_search_core_low_memory.py
ms_entropy/entropy_search/flash_entropy_search_core_medium_memory.py
ms_entropy/file_io/__init__.py
ms_entropy/file_io/lbm2_file.py
ms_entropy/file_io/mgf_file.py
ms_entropy/file_io/msp_file.py
ms_entropy/file_io/mzml_file.py
ms_entropy/file_io/shared.py
ms_entropy/file_io/spec_file.py
ms_entropy/spectra/__init__.py
ms_entropy/spectra/entropy.py
ms_entropy/spectra/entropy_cython.cp38-win_amd64.pyd
ms_entropy/spectra/entropy_numba.py
ms_entropy/spectra/tools.py
tests/ms_entropy/__init__.py
tests/ms_entropy/version.py
tests/ms_entropy/entropy_search/__init__.py
tests/ms_entropy/entropy_search/fast_flash_entropy_search.py
tests/ms_entropy/entropy_search/flash_entropy_search.py
tests/ms_entropy/entropy_search/flash_entropy_search_core.py
tests/ms_entropy/entropy_search/flash_entropy_search_core_for_dynamic_indexing.py
tests/ms_entropy/entropy_search/flash_entropy_search_core_low_memory.py
tests/ms_entropy/entropy_search/flash_entropy_search_core_medium_memory.py
tests/ms_entropy/file_io/__init__.py
tests/ms_entropy/file_io/lbm2_file.py
tests/ms_entropy/file_io/mgf_file.py
tests/ms_entropy/file_io/msp_file.py
tests/ms_entropy/file_io/mzml_file.py
tests/ms_entropy/file_io/shared.py
tests/ms_entropy/file_io/spec_file.py
tests/ms_entropy/spectra/__init__.py
tests/ms_entropy/spectra/entropy.py
tests/ms_entropy/spectra/entropy_numba.py
tests/ms_entropy/spectra/tools.py
ms_entropy-1.4.0.dist-info/LICENSE
ms_entropy-1.4.0.dist-info/METADATA
ms_entropy-1.4.0.dist-info/WHEEL
ms_entropy-1.4.0.dist-info/top_level.txt
ms_entropy-1.4.0.dist-info/RECORD
