Metadata-Version: 2.4
Name: ms_entropy
Version: 1.4.0
Summary: Python implementation of spectral entropy, entropy similarity, and Flash entropy search for mass spectrometry data.
Home-page: https://github.com/YuanyueLi/MSEntropy
Author-email: Yuanyue Li <yuanyueli@zju.edu.cn>
Project-URL: Homepage, https://github.com/YuanyueLi/MSEntropy
Project-URL: Bug Tracker, https://github.com/YuanyueLi/MSEntropy/issues
Keywords: mass spectrometry,ms entropy,entropy,spectral entropy,entropy similarity,flash entropy,flash entropy similarity,flash entropy search
Platform: Linux
Platform: MacOS
Platform: Windows
Classifier: Programming Language :: Python :: 3
Classifier: Programming Language :: Python :: 3 :: Only
Classifier: Programming Language :: Python :: 3.9
Classifier: Programming Language :: Python :: 3.10
Classifier: Programming Language :: Python :: 3.11
Classifier: Programming Language :: Python :: 3.12
Classifier: Operating System :: OS Independent
Requires-Python: >=3.7
License-File: LICENSE
Requires-Dist: numpy>=1.9.13
Provides-Extra: all
Requires-Dist: lz4>=4.3.2; extra == "all"
Requires-Dist: msgpack>=1.0.5; extra == "all"
Requires-Dist: pyteomics>=4.6; extra == "all"
Provides-Extra: gpu
Requires-Dist: cupy>=12.0.0; extra == "gpu"
Provides-Extra: dev
Requires-Dist: build; extra == "dev"
Requires-Dist: pytest; extra == "dev"
Requires-Dist: cython>=0.26.1; extra == "dev"
Dynamic: home-page
Dynamic: license-file
Dynamic: requires-python
